Workbook

Sheet Read Me
A1: FINANCIAL RUIN — 2 Month Content Plan
A2: 8 weeks · 1 long-form + 3 shorts per week · 32 assets total
A5: HOW TO USE
A6: Content Calendar | B6: The plan. Pick the week, copy the LONG TITLE, paste it into the DeepSeek prompt template. That is the whole workflow.
A7: Production Tracker | B7: Maryam's screen. One row per asset. She marks each stage Done as she goes. Titles pull automatically from the Calendar.
A8: Performance | B8: Fill in views + RPM after publishing. Yellow cells only. It works out revenue and how far you are from $100/day.
A9: Title Bank | B9: Spare titles for month 3 onward, plus the rules for writing your own.
A11: WEEKLY RHYTHM
A12: Monday | B12: Long-form goes live (12-16 min).
A13: Wednesday | B13: Short 1.
A14: Friday | B14: Short 2.
A15: Sunday | B15: Short 3.
B16: Shorts are cut from the long video's own images and audio. No new production. Each short is one self-contained beat, not a trailer.
A18: THE STRUCTURE VARIANT COLUMN
A19: Why it exists | B19: This is the single most important column in the file. YouTube's inauthentic-content policy targets template + low variation + replicable at scale. Eight identical scripts is the pattern that gets a channel demonetized.
A20: Rule | B20: Never use the same variant twice in a row. The Calendar already alternates all eight for you. If you swap a title, swap the variant with it.
A22: THE MECHANISM SECTION
A23: Never skip it | B23: The last 2 minutes of every long video explain how the scheme worked and the 3 signals people missed. That section is your original value. Without it the video is a slideshow. With it, it is analysis.
A25: SOURCING
A26: Rule | B26: Use publicly documented cases only — court records, DOJ / SEC / FTC press releases, state AG filings, local news archives. Never let the model invent a case and present it as real.
A27: If composite | B27: Say so on screen and in the description: 'A composite of documented cases. Names and details changed.' Then you are safe and honest at the same time.
A28: Never | B28: Do not name anyone who was not convicted or did not settle publicly. Do not accuse. Describe what the record says.
A30: DISCLOSURE
A31: At upload | B31: Tick 'Altered or synthetic content' in YouTube Studio. AI images of realistic scenes require it. Disclosing does not reduce your reach or your RPM — not disclosing costs you the channel.
A33: THE THREE STEPS
A34: Step 1 | B34: Open Content Calendar. Copy the green USER PROMPT cell for this week.
A35: Step 2 | B35: New DeepSeek chat. Paste the System Prompt tab first. Then paste the green cell. You get the script, plain paragraphs, nothing else.
A36: Step 3 | B36: New chat. Paste the Image Prompt tab, then paste the script into it. You get eighteen image prompts. Both go on Maryam's page.
A38: WHAT IS FIXED AND WHAT IS NOT
A39: Fixed | B39: Mode and sourcing rules live inside the System Prompt. You never touch them.
A40: Not fixed | B40: The STRUCTURE line changes every week and it is already written into the green cell. Do not make all eight the same. That sameness is what gets channels demonetized.

Sheet System Prompt
A1: SYSTEM PROMPT — paste this once, as the first message
A2: New chat for every video. System prompt first, then the USER PROMPT cell from the Content Calendar.
A4: You are the head writer for "The Ledger", a documentary channel about money crime. You write for a single narrator: a middle-aged American man with a quiet, unhurried delivery. He is not angry. He is not shocked. He has read the case file and he is telling you what is in it. Your script is read aloud by a text-to-speech engine and played over still photographic images with slow camera movement. There is no music under the narration. Nothing on screen moves. The sentences carry everything. MODE Every script is a COMPOSITE. You construct the case from patterns that genuinely recur in this type of fraud. You never present it as a specific real event, you never use a real person's name, and you never name a real company or institution. If the user supplies real case facts, use only those facts and add nothing. VOICE, these are rules and not suggestions 1. Vary sentence length deliberately. A long sentence that builds, then a short one that lands. Never three long sentences in a row, never three short ones. 2. Concrete over abstract, always. Not "he stole a significant sum" but "he took forty-one thousand dollars in the first year alone". 3. Trust silence. End a passage on a plain statement of fact and stop. Never add a summarising line. Never tell the viewer how to feel. 4. These words and phrases are banned entirely: shocking, unbelievable, devastating, heartbreaking, chilling, little did they know, little did he know, what happened next, the truth is, in a world where, and just like that. If one appears, delete the sentence and write a fact instead. 5. No rhetorical questions anywhere in the script. Not one. 6. No direct address to the viewer unless the STRUCTURE line explicitly asks for second person. 7. Use people's first names plainly and repeatedly. "Dolores", never "the victim" or "the woman in question". 8. Numbers are the drama. Exact figures, exact dates, exact durations. Round numbers feel invented, precise ones feel documented. 9. No financial advice, ever. The narrator observes patterns. He never tells the viewer what to do with their money. TEXT TO SPEECH FORMATTING, the script goes straight into a TTS engine Write every number, currency amount and date in words. Say "eighty four thousand dollars", "nineteen seventy eight", "six forty in the morning". Never write a digit. Never write a currency symbol or a percent sign. No em dashes. Use a full stop or a comma. A TTS engine reads an em dash as nothing and destroys the pause you wanted. No parentheses, brackets, asterisks, quotation marks around thoughts, bullet points, headings, or any markdown of any kind. No abbreviations or acronyms. Write the words out. Paragraphs of two to four sentences with a blank line between them. Each paragraph is one TTS chunk. Where you want a pause, end the sentence. Never use ellipses. WHAT YOU ARE WRITING One continuous narration of nineteen hundred to twenty three hundred words, which runs twelve to fifteen minutes at this narrator's pace. Internally it moves through six movements, but you never label them and never break them out on the page. The reader should feel the shape without being shown it. Movement one, about one hundred and sixty words: a cold, specific moment with no context given. Movement two, about four hundred words: the world and the people before anything went wrong. Make the person at the centre of it likeable. The viewer must trust him. Movement three, about four hundred and forty words: how he came to be near the money. Every step of it looked reasonable at the time. Movement four, about four hundred words: the first small thing that did not add up, and the reason nobody followed it. Movement five, about four hundred and forty words: the discovery and the collapse. Give the full figures here, the number of people, the number of years. Movement six, about three hundred words: how the scheme actually worked mechanically, then three signals that were present and were missed, stated as observations and not as warnings. This final movement must contain at least one insight that appears nowhere else in the script. End on one flat sentence with no lesson attached. The STRUCTURE line in the user message tells you how to order and enter the story. Follow it exactly. It overrides the default order above, but all six movements must still be present and hit roughly their lengths. OUTPUT Output the narration and nothing else. No title, no headings, no labels, no word counts, no notes, no preamble, no closing remarks. Plain paragraphs separated by blank lines. Begin with the first sentence of the script.
A6: API settings: model = deepseek-v4-pro | temperature = 1.4 | max_tokens = 6000 | top_p = 0.95
A7: Order: system message first, user message second. One video per chat. Never reuse a chat, the previous script will bleed into the next one.

Sheet Image Prompt
A1: IMAGE PROMPT — second call, after the script is done
A2: Fresh chat. No system prompt needed. Paste this, then paste the script where it says PASTE SCRIPT HERE.
A4: You turn a documentary narration into image generation prompts for an SDXL realistic model. The images will be shown as stills with slow pan and zoom. Nothing moves. Read the script I give you and produce eighteen prompts, in the order the images should appear. Rules for every prompt: Each prompt is a place, an object, or a wide human figure whose face is not readable. Never a close portrait. Never a recognisable real person. Never text, signage, logos or numbers in the frame. Each prompt contains, in this order: subject, setting, period markers, time of day, quality of light, lens and film character, colour grade. Vary the shot scale. Across every group of three, give one wide, one medium, one close detail. Hold one consistent look across all eighteen. Decide the grade in the first prompt and do not drift. Append this to the end of every single prompt, exactly as written: 35mm film photography, shallow depth of field, natural light, muted desaturated color grade, fine grain, no text, no watermark, photorealistic Output exactly eighteen numbered lines and nothing else. No preamble, no explanation. After the eighteen, output one line beginning NEGATIVE: followed by a single negative prompt for the whole set. Here is the script: [PASTE SCRIPT HERE]
A6: Use deepseek-v4-flash here. It is cheaper and this task does not need reasoning. Temperature 0.9.
A7: Output goes straight onto Maryam's page. She copies each line into Tensor.art and saves as 01.png through 18.png.

Sheet Content Calendar
A1: CONTENT CALENDAR — 8 Weeks
A2: Long-form publishes Monday. Shorts publish Wed / Fri / Sun, cut from the same long.
A4: Week | B4: Publish (Mon) | C4: Sub-Type | D4: Structure Variant | E4: LONG-FORM TITLE | F4: Thumbnail Text | G4: Opening Line | H4: SHORT 1 (Wed) | I4: SHORT 2 (Fri) | J4: SHORT 3 (Sun) | K4: USER PROMPT — copy this whole cell
A5: 1 | B5: 46265 | C5: Insider / Trusted Custodian | D5: 1. Cold open, then rewind | E5: They Called Him The Church Treasurer | F5: NINE YEARS | G5: On a Tuesday morning, Dolores walked into her bank and was told her account had been closed nine months earlier. She had been depositing into it every single Friday. | H5: The Deposit Slip That Didn't Match | I5: Nobody Checked The Ledger For Nine Years | J5: The One Question That Ended It | K5: TITLE: They Called Him The Church Treasurer STRUCTURE: Cold open, then rewind. Open on the bank scene with no context, then go back nine years and move forward chronologically to the discovery.
A6: 2 | B6: 46272 | C6: Elder Romance Fraud | D6: 2. Straight chronological | E6: She Was Seventy-Nine And She Was Sure She Was In Love | F6: HE NEVER ASKED | G6: He never asked her for money. Not once. That was the whole design. | H6: He Never Asked For Money. Not Once. | I6: The Photo Was Eleven Years Old | J6: Her Bank Tried To Stop Her Three Times | K6: TITLE: She Was Seventy-Nine And She Was Sure She Was In Love STRUCTURE: Straight chronological. Begin at the first contact and move forward without jumping. Let the slowness of it be the point.
A7: 3 | B7: 46279 | C7: Contractor / Home Repair | D7: 3. Reverse — open at the verdict | E7: The Roof Was Never Fixed | F7: $84,000 | G7: The county has a file on this man that is four inches thick. It begins with a roof that was never fixed. | H7: $84,000 For A Roof That Never Existed | I7: The Permit Was Real. The Company Wasn't. | J7: Why The Deposit Is Always Fifty Percent | K7: TITLE: The Roof Was Never Fixed STRUCTURE: Reverse. Open at the verdict, then work backwards through how it was built, ending at the very first handshake.
A8: 4 | B8: 46286 | C8: Ponzi / Community Collapse | D8: 4. Parallel timelines — victim & operator | E8: Everyone In Town Was Invested | F8: THE WHOLE TOWN | G8: By the sixth year, there were more people in that town invested with him than there were people who were not. | H8: The Returns Never Dropped. Not Once. In Six Years. | I8: How One Barber Shop Recruited An Entire Town | J8: The Month The Withdrawals Started | K8: TITLE: Everyone In Town Was Invested STRUCTURE: Parallel timelines. Alternate between what the investors believed was happening and what was actually happening, same dates, both threads.
A9: 5 | B9: 46293 | C9: Insurance Denial | D9: 5. Document-led — each act opens on paper | E9: The Policy Covered Everything Except This | F9: ONE SENTENCE | G9: She paid the premium for thirty-one years. The letter that ended it was four paragraphs long. | H9: Thirty Years Of Premiums. One Sentence. | I9: The Word That Voided Her Claim | J9: Why They Waited Until Day Eighty-Nine | K9: TITLE: The Policy Covered Everything Except This STRUCTURE: Document led. Each part of the story opens on a single piece of paper: an application, a statement, a letter, a denial.
A10: 6 | B10: 46300 | C10: Family / Long-Term Insider | D10: 6. Second person open, then pull back | E10: My Father Trusted Him For Twenty-Two Years | F10: 22 YEARS | G10: You would have trusted him too. That is not a figure of speech. Everybody did. | H10: He Signed The Checks For Twenty-Two Years | I10: The Accountant Who Never Took A Vacation | J10: Why Fraud Hides Behind Loyalty | K10: TITLE: My Father Trusted Him For Twenty-Two Years STRUCTURE: Second person, then pull back. Open addressing the viewer directly for two paragraphs, then drop into third person for the rest and never return.
A11: 7 | B11: 46307 | C11: Impersonation / Phone Scam | D11: 7. Numbers first — open on the final figure | E11: The Call Came At Six Forty In The Morning | F11: 6:40 AM | G11: Four hundred and twelve thousand dollars. That is what the morning cost her, and it started with a ringing phone. | H11: Six Forty AM Is Not An Accident | I11: The Voice On The Phone Was Her Grandson | J11: Why They Told Her Not To Hang Up | K11: TITLE: The Call Came At Six Forty In The Morning STRUCTURE: Numbers first. Open on the final loss figure, then show how that number was assembled, one increment at a time.
A12: 8 | B12: 46314 | C12: Professional Advisor | D12: 8. Aftermath first — five years later, then back | E12: The Man Who Sold Certainty | F12: NO LICENSE | G12: Five years later the office is a nail salon. The people who walked into it are still paying for what happened there. | H12: He Had A Corner Office And No License | I12: The Brochure Cost More Than The Fund | J12: Certainty Is The Product. Not Returns. | K12: TITLE: The Man Who Sold Certainty STRUCTURE: Aftermath first. Open five years later on what the place looks like now, then go back to the beginning.

Sheet Production Tracker
A1: PRODUCTION TRACKER
A2: Maryam's sheet. Type Done in each stage as it is finished. Titles pull from the Content Calendar automatically.
A4: Week | B4: Type | C4: Title | D4: Script | E4: Images | F4: Voiceover | G4: Edit | H4: Thumbnail | I4: Uploaded | J4: Notes
A5: 1 | B5: LONG | C5: ='Content Calendar'!E5 -> They Called Him The Church Treasurer
A6: 1 | B6: Short 1 | C6: ='Content Calendar'!H5 -> The Deposit Slip That Didn't Match
A7: 1 | B7: Short 2 | C7: ='Content Calendar'!I5 -> Nobody Checked The Ledger For Nine Years
A8: 1 | B8: Short 3 | C8: ='Content Calendar'!J5 -> The One Question That Ended It
A9: 2 | B9: LONG | C9: ='Content Calendar'!E6 -> She Was Seventy-Nine And She Was Sure She Was In Love
A10: 2 | B10: Short 1 | C10: ='Content Calendar'!H6 -> He Never Asked For Money. Not Once.
A11: 2 | B11: Short 2 | C11: ='Content Calendar'!I6 -> The Photo Was Eleven Years Old
A12: 2 | B12: Short 3 | C12: ='Content Calendar'!J6 -> Her Bank Tried To Stop Her Three Times
A13: 3 | B13: LONG | C13: ='Content Calendar'!E7 -> The Roof Was Never Fixed
A14: 3 | B14: Short 1 | C14: ='Content Calendar'!H7 -> $84,000 For A Roof That Never Existed
A15: 3 | B15: Short 2 | C15: ='Content Calendar'!I7 -> The Permit Was Real. The Company Wasn't.
A16: 3 | B16: Short 3 | C16: ='Content Calendar'!J7 -> Why The Deposit Is Always Fifty Percent
A17: 4 | B17: LONG | C17: ='Content Calendar'!E8 -> Everyone In Town Was Invested
A18: 4 | B18: Short 1 | C18: ='Content Calendar'!H8 -> The Returns Never Dropped. Not Once. In Six Years.
A19: 4 | B19: Short 2 | C19: ='Content Calendar'!I8 -> How One Barber Shop Recruited An Entire Town
A20: 4 | B20: Short 3 | C20: ='Content Calendar'!J8 -> The Month The Withdrawals Started
A21: 5 | B21: LONG | C21: ='Content Calendar'!E9 -> The Policy Covered Everything Except This
A22: 5 | B22: Short 1 | C22: ='Content Calendar'!H9 -> Thirty Years Of Premiums. One Sentence.
A23: 5 | B23: Short 2 | C23: ='Content Calendar'!I9 -> The Word That Voided Her Claim
A24: 5 | B24: Short 3 | C24: ='Content Calendar'!J9 -> Why They Waited Until Day Eighty-Nine
A25: 6 | B25: LONG | C25: ='Content Calendar'!E10 -> My Father Trusted Him For Twenty-Two Years
A26: 6 | B26: Short 1 | C26: ='Content Calendar'!H10 -> He Signed The Checks For Twenty-Two Years
A27: 6 | B27: Short 2 | C27: ='Content Calendar'!I10 -> The Accountant Who Never Took A Vacation
A28: 6 | B28: Short 3 | C28: ='Content Calendar'!J10 -> Why Fraud Hides Behind Loyalty
A29: 7 | B29: LONG | C29: ='Content Calendar'!E11 -> The Call Came At Six Forty In The Morning
A30: 7 | B30: Short 1 | C30: ='Content Calendar'!H11 -> Six Forty AM Is Not An Accident
A31: 7 | B31: Short 2 | C31: ='Content Calendar'!I11 -> The Voice On The Phone Was Her Grandson
A32: 7 | B32: Short 3 | C32: ='Content Calendar'!J11 -> Why They Told Her Not To Hang Up
A33: 8 | B33: LONG | C33: ='Content Calendar'!E12 -> The Man Who Sold Certainty
A34: 8 | B34: Short 1 | C34: ='Content Calendar'!H12 -> He Had A Corner Office And No License
A35: 8 | B35: Short 2 | C35: ='Content Calendar'!I12 -> The Brochure Cost More Than The Fund
A36: 8 | B36: Short 3 | C36: ='Content Calendar'!J12 -> Certainty Is The Product. Not Returns.
A38: Yellow cells = fill in. Everything else updates itself.

Sheet Performance
A1: PERFORMANCE — tracking toward $100/day
A2: Fill the yellow columns from YouTube Studio. Everything else calculates.
A4: Week | B4: Long-Form Title | C4: Views (long) | D4: Views (3 shorts) | E4: Long RPM ($) | F4: Shorts RPM ($) | G4: Est. Revenue ($) | H4: Avg View Duration
A5: 1 | B5: ='Content Calendar'!E5 -> They Called Him The Church Treasurer | G5: =IFERROR(C5/1000*E5+D5/1000*F5,0) -> 0
A6: 2 | B6: ='Content Calendar'!E6 -> She Was Seventy-Nine And She Was Sure She Was In Love | G6: =IFERROR(C6/1000*E6+D6/1000*F6,0) -> 0
A7: 3 | B7: ='Content Calendar'!E7 -> The Roof Was Never Fixed | G7: =IFERROR(C7/1000*E7+D7/1000*F7,0) -> 0
A8: 4 | B8: ='Content Calendar'!E8 -> Everyone In Town Was Invested | G8: =IFERROR(C8/1000*E8+D8/1000*F8,0) -> 0
A9: 5 | B9: ='Content Calendar'!E9 -> The Policy Covered Everything Except This | G9: =IFERROR(C9/1000*E9+D9/1000*F9,0) -> 0
A10: 6 | B10: ='Content Calendar'!E10 -> My Father Trusted Him For Twenty-Two Years | G10: =IFERROR(C10/1000*E10+D10/1000*F10,0) -> 0
A11: 7 | B11: ='Content Calendar'!E11 -> The Call Came At Six Forty In The Morning | G11: =IFERROR(C11/1000*E11+D11/1000*F11,0) -> 0
A12: 8 | B12: ='Content Calendar'!E12 -> The Man Who Sold Certainty | G12: =IFERROR(C12/1000*E12+D12/1000*F12,0) -> 0
B13: TOTAL (8 weeks) | C13: =SUM(C5:C12) -> 0 | D13: =SUM(D5:D12) -> 0 | G13: =SUM(G5:G12) -> 0
B16: THE $100/DAY MATH
B17: Target per day | C17: 100
B18: Target per month (30 days) | C18: =C17*30 -> 3000
B19: Your blended RPM so far | C19: =IFERROR(G13/((C13+D13)/1000),0) -> 0
B20: Monthly views needed at that RPM | C20: =IFERROR(C18/C19*1000,0) -> 0
B21: Your last-8-week views | C21: =C13+D13 -> 0
B22: Percent of the way there | C22: =IFERROR((C13+D13)/2/C20,0) -> 0
B24: Percent assumes your 8-week views represent roughly 2 months, halved to a monthly figure.
B25: Realistic RPM band for this niche with US/EU audience: $10-$25. Do not fill in $25 and plan around it.

Sheet Title Bank
A1: TITLE BANK — month 3 onward
A2: Same rules. Move one up into the Calendar when a week frees up.
A4: # | B4: Sub-Type | C4: LONG-FORM TITLE | D4: Why it works
A5: 1 | B5: Insider / Custodian | C5: The Bookkeeper Worked Late Every Night For Eleven Years | D5: Devotion reframed as method. Familiar detail, sinister on second read.
A6: 2 | B6: Elder Fraud | C6: They Told Her Not To Tell Her Son | D6: Isolation is the mechanism. The title names it without explaining it.
A7: 3 | B7: Ponzi | C7: The First Twelve Investors Got Paid In Full | D7: True statement that sounds like good news. That is the hook.
A8: 4 | B8: Insurance | C8: The Fire Was Real. The Claim Was Not. | D8: Two sentences, one reversal. Very high CTR structure.
A9: 5 | B9: Charity Fraud | C9: Ninety-One Cents Of Every Dollar | D9: A number nobody can resist finishing.
A10: 6 | B10: Contractor | C10: He Had Forty-Three Reviews And All Of Them Were Real | D10: Breaks the viewer's assumed defence. Curiosity gap is immediate.
A11: 7 | B11: Advisor | C11: The Statements Always Arrived On Time | D11: Reliability as camouflage. Quiet, ominous, no clickbait punctuation.
A12: 8 | B12: Employment Scam | C12: The Job Was Real Until The Second Week | D12: Time marker creates a question with a definite answer.
A13: 9 | B13: Crypto / Fintech | C13: Nobody Could Explain How It Made Money | D13: Everyone recognises this feeling. Universal entry point.
A14: 10 | B14: Family | C14: She Had Power Of Attorney | D14: Six words. Anyone who has aged parents feels this instantly.
A15: 11 | B15: Bank / Institution | C15: The Wire Cleared In Four Minutes | D15: Speed as the villain. Concrete, cinematic, visual.
A16: 12 | B16: Estate Fraud | C16: The Will Was Changed Nineteen Days Before | D16: Precise number implies documentation. Signals a real case.
B19: RULES FOR WRITING YOUR OWN
B20: • | C20: Understate it. This audience does not click SHOCKING or EXPOSED. They click a quiet sentence that implies something bad.
B21: • | C21: Use one concrete number or one concrete object. Nine years. A deposit slip. A roof. Abstractions do not get clicked.
B22: • | C22: Never put the answer in the title. 'They Called Him The Church Treasurer' works. 'Church Treasurer Steals $2M' does not.
B23: • | C23: No emoji, no ALL CAPS, no question marks. Those signal a different genre and pull in a lower-value audience.
B24: • | C24: Six to nine words. Long enough to feel like a sentence, short enough to survive the mobile crop.
B25: • | C25: Read it out loud. If it sounds like a documentary voiceover would say it, keep it.
